{
  "Id": "movvH08aD523519",
  "Genres": [
    {
      "Url": "https://fsharephim.com/genre/kinh-di/",
      "Name": "Kinh Dị"
    },
    {
      "Url": "https://fsharephim.com/genre/thriller/",
      "Name": "Thriller"
    }
  ],
  "Images": [
    {
      "Thumbnail": "https://image.tmdb.org/t/p/w300/5UaANddcbWFvFlikG9wpn1ZmKXr.jpg",
      "Url": "https://image.tmdb.org/t/p/original/5UaANddcbWFvFlikG9wpn1ZmKXr.jpg",
      "Name": "Anonymous 616"
    },
    {
      "Thumbnail": "https://image.tmdb.org/t/p/w300/ctW5SQCvWUiAnJwzWX7w7EhZ3iq.jpg",
      "Url": "https://image.tmdb.org/t/p/original/ctW5SQCvWUiAnJwzWX7w7EhZ3iq.jpg",
      "Name": "Anonymous 616"
    },
    {
      "Thumbnail": "https://image.tmdb.org/t/p/w300/bGonpJmfTx5qGQD8JkDayxTVxT0.jpg",
      "Url": "https://image.tmdb.org/t/p/original/bGonpJmfTx5qGQD8JkDayxTVxT0.jpg",
      "Name": "Anonymous 616"
    },
    {
      "Thumbnail": "https://image.tmdb.org/t/p/w300/zyKyByV4R4aCV6V769ZW3nh0MOL.jpg",
      "Url": "https://image.tmdb.org/t/p/original/zyKyByV4R4aCV6V769ZW3nh0MOL.jpg",
      "Name": "Anonymous 616"
    }
  ],
  "Links": [
    {
      "OriginalLink": "https://fsharephim.com/links/movvh08ad523519/",
      "Size": "2.32 GB",
      "FileSize": 2494136466,
      "IsAlive": true,
      "Url": "https://www.fshare.vn/file/HUL6QXA83EGUNG2",
      "Name": "Anonymous.616.2018.1080p.AMZ.WEB-DL.DD2.0.H264-NTG(77).mkv"
    }
  ],
  "Intro": "A reunion between two couples becomes a massacre when one of the guests meets an anonymous person online and willingly becomes a participant on a bloody path to becoming God-like.",
  "Poster": "https://fsharephim.com/wp-content/uploads/2018/05/fek93Bx15t59LlAkDqqnHmwveBI-185x278.jpg",
  "Trailer": "https://www.youtube.com/embed/wjecWlm-34M?rel=0&amp;controls=1&amp;showinfo=0&autoplay=0",
  "Seasons": null,
  "Url": "https://fsharephim.com/movies/anonymous-616/",
  "Name": "Anonymous 616"
}