{
  "Id": "movchu9JT485415",
  "Genres": [
    {
      "Url": "https://fsharephim.com/genre/kinh-di/",
      "Name": "Kinh Dị"
    }
  ],
  "Images": [
    {
      "Thumbnail": "https://image.tmdb.org/t/p/w300/vZDwvMO5ECnJxRaspKl9KoyVIEG.jpg",
      "Url": "https://image.tmdb.org/t/p/original/vZDwvMO5ECnJxRaspKl9KoyVIEG.jpg",
      "Name": "Day of the Dead: Bloodline"
    }
  ],
  "Links": [
    {
      "OriginalLink": "https://fsharephim.com/links/movchu9jt485415/",
      "Size": "3.1 GB",
      "FileSize": 3316889639,
      "IsAlive": true,
      "Url": "https://www.fshare.vn/file/ASX27HJYZRJ7",
      "Name": "Day.of.the.Dead.Bloodline.2018.1080p.WEB-DL.DD5.1.H264-FGT.mkv"
    }
  ],
  "Intro": "In a world overrun by zombies, military personnel and survivalists live in an underground bunker while they seek a cure.",
  "Poster": "https://fsharephim.com/wp-content/uploads/2018/01/3jM4C1wJxHLWlF4tcSyyv6fnJPR-185x278.jpg",
  "Trailer": "https://www.youtube.com/embed/3hhFT3vCeko?rel=0&amp;controls=1&amp;showinfo=0&autoplay=0",
  "Seasons": null,
  "Url": "https://fsharephim.com/movies/day-of-the-dead-bloodline/",
  "Name": "Day of the Dead: Bloodline"
}