{
  "Id": "movL1zJz8502426",
  "Genres": [
    {
      "Url": "https://fsharephim.com/genre/hai-huoc/",
      "Name": "Hài Hước"
    }
  ],
  "Images": [
    {
      "Thumbnail": "https://image.tmdb.org/t/p/w300/7iFaPlDU4PnG2GOR6PQgvpUe3kL.jpg",
      "Url": "https://image.tmdb.org/t/p/original/7iFaPlDU4PnG2GOR6PQgvpUe3kL.jpg",
      "Name": "Furlough"
    },
    {
      "Thumbnail": "https://image.tmdb.org/t/p/w300/hb127W13xThbwH0IOM3M0szSgwD.jpg",
      "Url": "https://image.tmdb.org/t/p/original/hb127W13xThbwH0IOM3M0szSgwD.jpg",
      "Name": "Furlough"
    }
  ],
  "Links": [
    {
      "OriginalLink": "https://fsharephim.com/links/movl1zjz8502426/",
      "Size": "2.87 GB",
      "FileSize": 0,
      "IsAlive": false,
      "Url": "http://www.fshare.vn/file/IE5BSSAQLJNB",
      "Name": "WEB-DL-1080p"
    }
  ],
  "Intro": "When an inmate is granted one weekend out of prison to see her dying mother, a rookie correction officer struggles to keep her under control.",
  "Poster": "https://fsharephim.com/wp-content/uploads/2018/03/cw1RkjmbNfIbujkPGh6a8J9Lrf1-185x278.jpg",
  "Trailer": "https://www.youtube.com/embed/AT6fsehV4z4?rel=0&amp;controls=1&amp;showinfo=0&autoplay=0",
  "Seasons": null,
  "Url": "https://fsharephim.com/movies/furlough/",
  "Name": "Furlough"
}