{
  "Id": null,
  "Genres": [
    {
      "Url": "https://fsharephim.com/genre/hai-huoc/",
      "Name": "Hài Hước"
    },
    {
      "Url": "https://fsharephim.com/genre/kinh-di/",
      "Name": "Kinh Dị"
    },
    {
      "Url": "https://fsharephim.com/genre/ky-ao/",
      "Name": "Kỳ Ảo"
    }
  ],
  "Images": [
    {
      "Thumbnail": "https://image.tmdb.org/t/p/w300/5GsJuYZuG1bkuSI8FeWol5nvR9S.jpg",
      "Url": "https://image.tmdb.org/t/p/original/5GsJuYZuG1bkuSI8FeWol5nvR9S.jpg",
      "Name": "Krampus"
    },
    {
      "Thumbnail": "https://image.tmdb.org/t/p/w300/q90pybT14OTcIOlfItGV2u3vcQF.jpg",
      "Url": "https://image.tmdb.org/t/p/original/q90pybT14OTcIOlfItGV2u3vcQF.jpg",
      "Name": "Krampus"
    },
    {
      "Thumbnail": "https://image.tmdb.org/t/p/w300/cQEaSBlIeFoCpTmZ3VAOh0Vh5PH.jpg",
      "Url": "https://image.tmdb.org/t/p/original/cQEaSBlIeFoCpTmZ3VAOh0Vh5PH.jpg",
      "Name": "Krampus"
    },
    {
      "Thumbnail": "https://image.tmdb.org/t/p/w300/baI5T5Ws1yp8pidn85ZXeTP3uqs.jpg",
      "Url": "https://image.tmdb.org/t/p/original/baI5T5Ws1yp8pidn85ZXeTP3uqs.jpg",
      "Name": "Krampus"
    },
    {
      "Thumbnail": "https://image.tmdb.org/t/p/w300/9cxnLP8CNGQhl3P3eVvIbCjXB22.jpg",
      "Url": "https://image.tmdb.org/t/p/original/9cxnLP8CNGQhl3P3eVvIbCjXB22.jpg",
      "Name": "Krampus"
    },
    {
      "Thumbnail": "https://image.tmdb.org/t/p/w300/5DqINV0CTIINaq4EfrRn7Hj1mUK.jpg",
      "Url": "https://image.tmdb.org/t/p/original/5DqINV0CTIINaq4EfrRn7Hj1mUK.jpg",
      "Name": "Krampus"
    }
  ],
  "Links": [],
  "Intro": "A horror comedy based on the ancient legend about a pagan creature who punishes children on Christmas.",
  "Poster": "https://fsharephim.com/wp-content/uploads/2018/02/27SiV4EBHcTBMz4IKANjhX5iIoX-185x278.jpg",
  "Trailer": "https://www.youtube.com/embed/9k-uig5obaA?rel=0&amp;controls=1&amp;showinfo=0&autoplay=0",
  "Seasons": null,
  "Url": "https://fsharephim.com/movies/krampus/",
  "Name": "Krampus"
}