{
  "Id": "movRXcoxo12230",
  "Url": "https://fsharephim.com/movies/one-hundred-and-one-dalmatians/",
  "Name": "Một trăm linh một chú chó đốm",
  "Links": [
    {
      "OriginalLink": "https://fsharephim.com/links/movrxcoxo12230-2/",
      "Name": "Bluray - Vie",
      "Url": "https://www.fshare.vn/file/ENTSC2W5NNZR",
      "Size": "23.55 GB",
      "FileSize": 0
    },
    {
      "OriginalLink": "https://fsharephim.com/links/movrxcoxo12230/",
      "Name": "101.Dalmatians.1961.mkv",
      "Url": "https://www.fshare.vn/file/TMC86HY5TT",
      "Size": "1.56 GB",
      "FileSize": 1670013992
    }
  ]
}