{
  "Id": "movVitzGH49529",
  "Genres": [
    {
      "Url": "https://fsharephim.com/genre/hanh-dong/",
      "Name": "Hành Động"
    },
    {
      "Url": "https://fsharephim.com/genre/khoa-hoc-vien-tuong/",
      "Name": "Khoa Học Viễn Tưởng"
    },
    {
      "Url": "https://fsharephim.com/genre/phieu-luu/",
      "Name": "Phiêu Lưu"
    }
  ],
  "Images": [
    {
      "Thumbnail": "https://image.tmdb.org/t/p/w300/2eDepJWMMBHmZ7pt9MSqzGQeoDc.jpg",
      "Url": "https://image.tmdb.org/t/p/original/2eDepJWMMBHmZ7pt9MSqzGQeoDc.jpg",
      "Name": "Người Hùng Sao Hỏa - John Carter"
    },
    {
      "Thumbnail": "https://image.tmdb.org/t/p/w300/qFrJlsJaKr0nIbyRQbb6bdTnkHZ.jpg",
      "Url": "https://image.tmdb.org/t/p/original/qFrJlsJaKr0nIbyRQbb6bdTnkHZ.jpg",
      "Name": "Người Hùng Sao Hỏa - John Carter"
    },
    {
      "Thumbnail": "https://image.tmdb.org/t/p/w300/2WQqfVnCZiLwZQm8hl6B42Qx1ft.jpg",
      "Url": "https://image.tmdb.org/t/p/original/2WQqfVnCZiLwZQm8hl6B42Qx1ft.jpg",
      "Name": "Người Hùng Sao Hỏa - John Carter"
    },
    {
      "Thumbnail": "https://image.tmdb.org/t/p/w300/efkpuifhYzaLjvGQ7Z8WPszcDIo.jpg",
      "Url": "https://image.tmdb.org/t/p/original/efkpuifhYzaLjvGQ7Z8WPszcDIo.jpg",
      "Name": "Người Hùng Sao Hỏa - John Carter"
    },
    {
      "Thumbnail": "https://image.tmdb.org/t/p/w300/kNyGNzUK4ocFeGIJoiNP7dnEBYu.jpg",
      "Url": "https://image.tmdb.org/t/p/original/kNyGNzUK4ocFeGIJoiNP7dnEBYu.jpg",
      "Name": "Người Hùng Sao Hỏa - John Carter"
    },
    {
      "Thumbnail": "https://image.tmdb.org/t/p/w300/wmyuA9Ce9cFLfviBeUvKKJNRP2U.jpg",
      "Url": "https://image.tmdb.org/t/p/original/wmyuA9Ce9cFLfviBeUvKKJNRP2U.jpg",
      "Name": "Người Hùng Sao Hỏa - John Carter"
    },
    {
      "Thumbnail": "https://image.tmdb.org/t/p/w300/dAafYWECE54Ac00LjAjQfh3Uimi.jpg",
      "Url": "https://image.tmdb.org/t/p/original/dAafYWECE54Ac00LjAjQfh3Uimi.jpg",
      "Name": "Người Hùng Sao Hỏa - John Carter"
    },
    {
      "Thumbnail": "https://image.tmdb.org/t/p/w300/rv9enC180H8sotlDwSiPD85hwmA.jpg",
      "Url": "https://image.tmdb.org/t/p/original/rv9enC180H8sotlDwSiPD85hwmA.jpg",
      "Name": "Người Hùng Sao Hỏa - John Carter"
    },
    {
      "Thumbnail": "https://image.tmdb.org/t/p/w300/mdeR7US9Aa9wDg32EVi4dWvvy4V.jpg",
      "Url": "https://image.tmdb.org/t/p/original/mdeR7US9Aa9wDg32EVi4dWvvy4V.jpg",
      "Name": "Người Hùng Sao Hỏa - John Carter"
    },
    {
      "Thumbnail": "https://image.tmdb.org/t/p/w300/2ZSt404xhhBIop3mgl5rz9ge0xf.jpg",
      "Url": "https://image.tmdb.org/t/p/original/2ZSt404xhhBIop3mgl5rz9ge0xf.jpg",
      "Name": "Người Hùng Sao Hỏa - John Carter"
    }
  ],
  "Links": [
    {
      "OriginalLink": "https://fsharephim.com/links/movvitzgh49529-6/",
      "Size": "3.0 GB",
      "FileSize": 3269238834,
      "IsAlive": true,
      "Url": "https://www.fshare.vn/file/9EX6UHIVM6PQDCD",
      "Name": "John Carter 2012 mHD ViE Bluray DD5.1 x264-EPiK-HDAT.mkv"
    },
    {
      "OriginalLink": "https://fsharephim.com/links/movvitzgh49529-5/",
      "Size": "7.0 GB",
      "FileSize": 7474746107,
      "IsAlive": true,
      "Url": "https://www.fshare.vn/file/RMKNA7XRTIUGFGR",
      "Name": "John Carter 3D 2012_phu de 3D noi.mkv"
    },
    {
      "OriginalLink": "https://fsharephim.com/links/movvitzgh49529-4/",
      "Size": "30.9 GB",
      "FileSize": 33124909056,
      "IsAlive": true,
      "Url": "https://www.fshare.vn/file/AHBTXYO9ZWAFZGY",
      "Name": "John Carter 2012 1080p Blu-Ray Remux AVC DTS-HD MA 7.1-Hanoi(1).iso"
    },
    {
      "OriginalLink": "https://fsharephim.com/links/movvitzgh49529-3/",
      "Size": "9.2 GB",
      "FileSize": 9845952597,
      "IsAlive": true,
      "Url": "https://www.fshare.vn/file/9NA5K4NO5EB5EDE",
      "Name": "John.Carter.2012.3D.3D.H-OU.ACM3D.1080p.Bluray.x264.z-man.mkv"
    },
    {
      "OriginalLink": "https://fsharephim.com/links/movvitzgh49529-2/",
      "Size": "6.8 GB",
      "FileSize": 7292712629,
      "IsAlive": true,
      "Url": "https://www.fshare.vn/file/ZRLCN2ZJGD7NEP4",
      "Name": "John.Carter.2012.720p.BluRay.x264.DTS-HDChina(1).mkv"
    },
    {
      "OriginalLink": "https://fsharephim.com/links/movvitzgh49529/",
      "Size": "2.7 GB",
      "FileSize": 2911990138,
      "IsAlive": true,
      "Url": "https://www.fshare.vn/file/SQ3X5OP8PLJPMQK",
      "Name": "John.Carter.2012.Bluray.mHD.720p.x264.AC3-TRiM™.mkv"
    }
  ],
  "Intro": "John Carter, một cựu binh tới từ bang Virginia, vốn là người chính trực và quả cảm, cuộc nội chiến trong thế kỷ 19 của nước Mỹ khiến anh cảm thấy chán nản và tuyệt vọng. Trong một lần đi khám phá hang động có chứa vàng, John Carter đột nhiên bị thế lực siêu nhiên nào đó đưa tới hành tinh Barsoom mà sau đó anh mới phát hiện ra đây chính là sao Hỏa. Trọng lực yếu ở đây giúp cho John Carter có khả năng nhảy cao và phi thân qua khoảng cách dài. Từ một người Trái đất bình thường, John trở thành siêu anh hùng trên sao Hỏa.",
  "Poster": "https://fsharephim.com/wp-content/uploads/2017/10/4QDBNt9PmxqUH4Ab2R5xKWqzXiQ-185x278.jpg",
  "Trailer": "https://www.youtube.com/embed/6Rf55GTEZ_E?rel=0&amp;controls=1&amp;showinfo=0&autoplay=0",
  "Seasons": null,
  "Url": "https://fsharephim.com/movies/john-carter/",
  "Name": "Người Hùng Sao Hỏa"
}