{
  "Id": null,
  "Genres": [
    {
      "Url": "https://fsharephim.com/genre/chinh-kich/",
      "Name": "Chính Kịch"
    },
    {
      "Url": "https://fsharephim.com/genre/thriller/",
      "Name": "Thriller"
    }
  ],
  "Images": [
    {
      "Thumbnail": "https://image.tmdb.org/t/p/w300/4hjQ4IKBO7N29tM5rnVGRGTJGyY.jpg",
      "Url": "https://image.tmdb.org/t/p/original/4hjQ4IKBO7N29tM5rnVGRGTJGyY.jpg ",
      "Name": "Overheard"
    },
    {
      "Thumbnail": "https://image.tmdb.org/t/p/w300/Aq6BVCncwecDATDe6fNmEkw3MxC.jpg",
      "Url": "https://image.tmdb.org/t/p/original/Aq6BVCncwecDATDe6fNmEkw3MxC.jpg ",
      "Name": "Overheard"
    }
  ],
  "Links": [],
  "Intro": "The story revolves around three members of a police surveillance squad conducting an investigation into a financial investment group involved in criminal fraud. The focus of the plot, however, is actually on the three officers themselves who stumble upon an opportunity to capitalize on information they gathered during their surveillance.",
  "Poster": "https://fsharephim.com/wp-content/uploads/2017/09/dl5yyUmJnmgPfbVDklpxbJFm2a1-185x278.jpg",
  "Trailer": "https://www.youtube.com/embed/r-uU-uCyZ0Q?rel=0&amp;controls=1&amp;showinfo=0&autoplay=0",
  "Seasons": null,
  "Url": "https://fsharephim.com/movies/overheard/",
  "Name": "Overheard"
}