{
  "Id": null,
  "Genres": [
    {
      "Url": "https://fsharephim.com/genre/hanh-dong/",
      "Name": "Hành Động"
    },
    {
      "Url": "https://fsharephim.com/genre/lang-man/",
      "Name": "Lãng Mạn"
    },
    {
      "Url": "https://fsharephim.com/genre/toi-pham/",
      "Name": "Tội Phạm"
    }
  ],
  "Images": [],
  "Links": [],
  "Intro": "Jack Maverick, một thám tử quốc tế bay đến thị trấn Passo Fundo, Brazil, để truy bắt một tên tội phạm giết người, nhưng Maverick nhận thấy mình đã rơi vào bẫy của băng đảng tội phạm địa phương, được điều hành bởi một tập đoàn ma túy xuyên quốc gia. Đề phá vỡ âm mưu bọn chúng, Maverick phải đối đầu với chúng thật gian nan, chúng đã vờn anh như mèo vờn chuột cho đến khi anh tiêu diệt được tên đầu sỏ cứu được cô gái đang bị chúng hành hình trong một trận đấu thư hùng&#8230;",
  "Poster": "https://fsharephim.com/wp-content/uploads/2018/03/eNRMjPX41IRUkchbkld7jVLRwxZ-185x278.jpg",
  "Trailer": null,
  "Seasons": null,
  "Url": "https://fsharephim.com/movies/maverick-manhunt-brazil/",
  "Name": "Săn Tội Phạm"
}