{
  "Id": null,
  "Genres": [
    {
      "Url": "https://fsharephim.com/genre/chinh-kich/",
      "Name": "Chính Kịch"
    },
    {
      "Url": "https://fsharephim.com/genre/hai-huoc/",
      "Name": "Hài Hước"
    },
    {
      "Url": "https://fsharephim.com/genre/hoat-hinh/",
      "Name": "Hoạt Hình"
    },
    {
      "Url": "https://fsharephim.com/genre/phieu-luu/",
      "Name": "Phiêu Lưu"
    }
  ],
  "Images": [
    {
      "Thumbnail": "https://image.tmdb.org/t/p/w300/qBRwRxhUszKvcHQxMiimuax6U2e.jpg",
      "Url": "https://image.tmdb.org/t/p/original/qBRwRxhUszKvcHQxMiimuax6U2e.jpg",
      "Name": "The Triplets of Belleville"
    },
    {
      "Thumbnail": "https://image.tmdb.org/t/p/w300/iGGOn3d3pQB5gBY7PvqN40ZYzWx.jpg",
      "Url": "https://image.tmdb.org/t/p/original/iGGOn3d3pQB5gBY7PvqN40ZYzWx.jpg",
      "Name": "The Triplets of Belleville"
    },
    {
      "Thumbnail": "https://image.tmdb.org/t/p/w300/oEWs0uDAK9IDm3z4VD0YUuyQEUs.jpg",
      "Url": "https://image.tmdb.org/t/p/original/oEWs0uDAK9IDm3z4VD0YUuyQEUs.jpg",
      "Name": "The Triplets of Belleville"
    },
    {
      "Thumbnail": "https://image.tmdb.org/t/p/w300/wjQbcQjFvSV5vmO9hyaRbbDkTs0.jpg",
      "Url": "https://image.tmdb.org/t/p/original/wjQbcQjFvSV5vmO9hyaRbbDkTs0.jpg",
      "Name": "The Triplets of Belleville"
    },
    {
      "Thumbnail": "https://image.tmdb.org/t/p/w300/khjMlfNaCmfJ8HXU3Cxtc0npLKg.jpg",
      "Url": "https://image.tmdb.org/t/p/original/khjMlfNaCmfJ8HXU3Cxtc0npLKg.jpg",
      "Name": "The Triplets of Belleville"
    },
    {
      "Thumbnail": "https://image.tmdb.org/t/p/w300/onDHczbjj9aQfcc65u6NqVDjxUn.jpg",
      "Url": "https://image.tmdb.org/t/p/original/onDHczbjj9aQfcc65u6NqVDjxUn.jpg",
      "Name": "The Triplets of Belleville"
    },
    {
      "Thumbnail": "https://image.tmdb.org/t/p/w300/qmJlCQa3QP5vtCwAK3inq4uY6Ef.jpg",
      "Url": "https://image.tmdb.org/t/p/original/qmJlCQa3QP5vtCwAK3inq4uY6Ef.jpg",
      "Name": "The Triplets of Belleville"
    }
  ],
  "Links": [],
  "Intro": "When her grandson is kidnapped during the Tour de France, Madame Souza and her beloved pooch Bruno team up with the Belleville Sisters&#8211;an aged song-and-dance team from the days of Fred Astaire&#8211;to rescue him.",
  "Poster": "https://fsharephim.com/wp-content/uploads/2017/09/A8aSp63Xi4cnip3wAhk7Jml1uWG-185x278.jpg",
  "Trailer": "https://www.youtube.com/embed/Npro9kjyaJk?rel=0&amp;controls=1&amp;showinfo=0&autoplay=0",
  "Seasons": null,
  "Url": "https://fsharephim.com/movies/the-triplets-of-belleville/",
  "Name": "The Triplets of Belleville"
}