{
  "Id": null,
  "Genres": [
    {
      "Url": "https://fsharephim.com/genre/chinh-kich/",
      "Name": "Chính Kịch"
    },
    {
      "Url": "https://fsharephim.com/genre/hanh-dong-va-phieu-luu/",
      "Name": "Hành Động và Phiêu Lưu"
    },
    {
      "Url": "https://fsharephim.com/genre/ky-ao-khoa-hoc/",
      "Name": "Kỳ Ảo Khoa Học"
    }
  ],
  "Images": [
    {
      "Thumbnail": "https://image.tmdb.org/t/p/w300/20txnfxxmpvqOdDqIiy2hO06qqG.jpg",
      "Url": "https://image.tmdb.org/t/p/original/20txnfxxmpvqOdDqIiy2hO06qqG.jpg",
      "Name": "The Last Ship"
    },
    {
      "Thumbnail": "https://image.tmdb.org/t/p/w300/5DzVsL6A5iMItCQxzVsU10lDhEQ.jpg",
      "Url": "https://image.tmdb.org/t/p/original/5DzVsL6A5iMItCQxzVsU10lDhEQ.jpg",
      "Name": "The Last Ship"
    },
    {
      "Thumbnail": "https://image.tmdb.org/t/p/w300/spC03EL1HQcRvrW4Ggl8sIz70TN.jpg",
      "Url": "https://image.tmdb.org/t/p/original/spC03EL1HQcRvrW4Ggl8sIz70TN.jpg",
      "Name": "The Last Ship"
    },
    {
      "Thumbnail": "https://image.tmdb.org/t/p/w300/7gVxVED3cN9YSwwP21AQdYpqUcr.jpg",
      "Url": "https://image.tmdb.org/t/p/original/7gVxVED3cN9YSwwP21AQdYpqUcr.jpg",
      "Name": "The Last Ship"
    },
    {
      "Thumbnail": "https://image.tmdb.org/t/p/w300/kg6PdI0Jkq850xGTbtSHOU3UcuS.jpg",
      "Url": "https://image.tmdb.org/t/p/original/kg6PdI0Jkq850xGTbtSHOU3UcuS.jpg",
      "Name": "The Last Ship"
    },
    {
      "Thumbnail": "https://image.tmdb.org/t/p/w300/aWYM1nCybrIMVhxACYEiJjCKuDJ.jpg",
      "Url": "https://image.tmdb.org/t/p/original/aWYM1nCybrIMVhxACYEiJjCKuDJ.jpg",
      "Name": "The Last Ship"
    },
    {
      "Thumbnail": "https://image.tmdb.org/t/p/w300/q6j5hYdZ7cR2F2TK5kD4c9bYroR.jpg",
      "Url": "https://image.tmdb.org/t/p/original/q6j5hYdZ7cR2F2TK5kD4c9bYroR.jpg",
      "Name": "The Last Ship"
    },
    {
      "Thumbnail": "https://image.tmdb.org/t/p/w300/pbqksWMWeTd2UZ58K7BOkGrLU9E.jpg",
      "Url": "https://image.tmdb.org/t/p/original/pbqksWMWeTd2UZ58K7BOkGrLU9E.jpg",
      "Name": "The Last Ship"
    },
    {
      "Thumbnail": "https://image.tmdb.org/t/p/w300/wQzTMMx8xc4ZbLpppXUwjSQduhc.jpg",
      "Url": "https://image.tmdb.org/t/p/original/wQzTMMx8xc4ZbLpppXUwjSQduhc.jpg",
      "Name": "The Last Ship"
    },
    {
      "Thumbnail": "https://image.tmdb.org/t/p/w300/8BMUJooemnuCVJjpPA87fTLOuTp.jpg",
      "Url": "https://image.tmdb.org/t/p/original/8BMUJooemnuCVJjpPA87fTLOuTp.jpg",
      "Name": "The Last Ship"
    }
  ],
  "Links": [
    {
      "OriginalLink": null,
      "Size": null,
      "FileSize": 0,
      "IsAlive": false,
      "Url": "https://fsharephim.com/episodes/the-last-ship-4x1/",
      "Name": "In Medias Res"
    },
    {
      "OriginalLink": null,
      "Size": null,
      "FileSize": 0,
      "IsAlive": false,
      "Url": "https://fsharephim.com/episodes/the-last-ship-4x2/",
      "Name": "The Pillars of Hercules"
    },
    {
      "OriginalLink": null,
      "Size": null,
      "FileSize": 0,
      "IsAlive": false,
      "Url": "https://fsharephim.com/episodes/the-last-ship-4x3/",
      "Name": "Bread and Circuses"
    },
    {
      "OriginalLink": null,
      "Size": null,
      "FileSize": 0,
      "IsAlive": false,
      "Url": "https://fsharephim.com/episodes/the-last-ship-4x4/",
      "Name": "Nostos"
    },
    {
      "OriginalLink": null,
      "Size": null,
      "FileSize": 0,
      "IsAlive": false,
      "Url": "https://fsharephim.com/episodes/the-last-ship-4x5/",
      "Name": "Allegiance"
    },
    {
      "OriginalLink": null,
      "Size": null,
      "FileSize": 0,
      "IsAlive": false,
      "Url": "https://fsharephim.com/episodes/the-last-ship-4x6/",
      "Name": "Tempest"
    },
    {
      "OriginalLink": null,
      "Size": null,
      "FileSize": 0,
      "IsAlive": false,
      "Url": "https://fsharephim.com/episodes/the-last-ship-4x7/",
      "Name": "Feast"
    },
    {
      "OriginalLink": null,
      "Size": null,
      "FileSize": 0,
      "IsAlive": false,
      "Url": "https://fsharephim.com/episodes/the-last-ship-4x8/",
      "Name": "Lazaretto"
    },
    {
      "OriginalLink": null,
      "Size": null,
      "FileSize": 0,
      "IsAlive": false,
      "Url": "https://fsharephim.com/episodes/the-last-ship-4x9/",
      "Name": "Detect, Deceive, Destroy"
    },
    {
      "OriginalLink": null,
      "Size": null,
      "FileSize": 0,
      "IsAlive": false,
      "Url": "https://fsharephim.com/episodes/the-last-ship-4x10/",
      "Name": "Endgame"
    }
  ],
  "Intro": "Their mission is simple: Find a cure. Stop the virus. Save the world. When a global pandemic wipes out eighty percent of the planet&#8217;s population, the crew of a lone naval destroyer must find a way to pull humanity from the brink of extinction.",
  "Poster": "https://fsharephim.com/wp-content/uploads/2017/10/zM6UvfOCxY6QtSVfJkhPG7rPW3c-185x278.jpg",
  "Trailer": "https://www.youtube.com/embed/4gZ6bpIjeLs?rel=0&amp;controls=1&amp;showinfo=0&autoplay=0",
  "Seasons": [
    {
      "Episodes": null,
      "Url": null,
      "Name": "Season 1 Jun. 22, 2014"
    },
    {
      "Episodes": null,
      "Url": null,
      "Name": "Season 2 Jun. 21, 2015"
    },
    {
      "Episodes": null,
      "Url": null,
      "Name": "Season 3 Jun. 19, 2016"
    },
    {
      "Episodes": [
        {
          "Id": "tvtxyo7V1320223",
          "Genres": [],
          "Images": [
            {
              "Thumbnail": "https://image.tmdb.org/t/p/w300/gneyP4xNpouTZww86YpAcKKkL9Z.jpg",
              "Url": "https://image.tmdb.org/t/p/original/gneyP4xNpouTZww86YpAcKKkL9Z.jpg",
              "Name": "The Last Ship 4&#215;1"
            },
            {
              "Thumbnail": "https://image.tmdb.org/t/p/w300/ivG8dWiSVBNmvSn2UHloPtE4DEd.jpg",
              "Url": "https://image.tmdb.org/t/p/original/ivG8dWiSVBNmvSn2UHloPtE4DEd.jpg",
              "Name": "The Last Ship 4&#215;1"
            },
            {
              "Thumbnail": "https://image.tmdb.org/t/p/w300/aBWPy7n7WXY1OpcecwCxkF8G424.jpg",
              "Url": "https://image.tmdb.org/t/p/original/aBWPy7n7WXY1OpcecwCxkF8G424.jpg",
              "Name": "The Last Ship 4&#215;1"
            }
          ],
          "Links": [
            {
              "OriginalLink": "https://fsharephim.com/links/tvtxyo7v1320223-2/",
              "Size": "--",
              "FileSize": 0,
              "IsAlive": false,
              "Url": "https://subscene.com/subtitles/the-last-ship-fourth-season/vietnamese/1617193",
              "Name": "Viet - Subtitle"
            },
            {
              "OriginalLink": "https://fsharephim.com/links/tvtxyo7v1320223/",
              "Size": "3.2 GB",
              "FileSize": 3415030587,
              "IsAlive": true,
              "Url": "https://www.fshare.vn/file/9ABFYCFX3DCCGVV",
              "Name": "The.Last.Ship.S04E01.1080p.AMZN.WEB-DL.DD5.1.H.264-QOQ.mkv"
            }
          ],
          "Intro": "Sixteen months after thwarting the coup in America, Nathan James must face yet another global disaster. The question remains, where in the world is Tom Chandler?",
          "Poster": null,
          "Trailer": null,
          "Seasons": null,
          "Url": "https://fsharephim.com/episodes/the-last-ship-4x1/",
          "Name": "The Last Ship 4x1"
        },
        {
          "Id": "tvtxyo7V1347244",
          "Genres": [],
          "Images": [
            {
              "Thumbnail": "https://image.tmdb.org/t/p/w300/tCabxFJyBol9Qqwfw5f8WMXJHWs.jpg",
              "Url": "https://image.tmdb.org/t/p/original/tCabxFJyBol9Qqwfw5f8WMXJHWs.jpg",
              "Name": "The Last Ship 4&#215;10"
            }
          ],
          "Links": [
            {
              "OriginalLink": "https://fsharephim.com/links/tvtxyo7v1347244/",
              "Size": "1001.4 MB",
              "FileSize": 1050046663,
              "IsAlive": true,
              "Url": "https://www.fshare.vn/file/G4X11UVJUBRLDV1",
              "Name": "The.Last.Ship.S04E10.720p.HDTV.X264-DIMENSION.mkv"
            }
          ],
          "Intro": "Chandler confronts his enemy — and his personal demons — in a final showdown, with the fate of humanity on the line.",
          "Poster": null,
          "Trailer": null,
          "Seasons": null,
          "Url": "https://fsharephim.com/episodes/the-last-ship-4x10/",
          "Name": "The Last Ship 4x10"
        },
        {
          "Id": "tvtxyo7V1345697",
          "Genres": [],
          "Images": [
            {
              "Thumbnail": "https://image.tmdb.org/t/p/w300/hrQlVbBEhcQVHsHpTBSMo0uJLIj.jpg",
              "Url": "https://image.tmdb.org/t/p/original/hrQlVbBEhcQVHsHpTBSMo0uJLIj.jpg",
              "Name": "The Last Ship 4&#215;2"
            }
          ],
          "Links": [
            {
              "OriginalLink": "https://fsharephim.com/links/tvtxyo7v1345697-2/",
              "Size": "--",
              "FileSize": 0,
              "IsAlive": false,
              "Url": "https://subscene.com/subtitles/the-last-ship-fourth-season/vietnamese/1617558",
              "Name": "Viet - Subtitle"
            },
            {
              "OriginalLink": "https://fsharephim.com/links/tvtxyo7v1345697/",
              "Size": "3.0 GB",
              "FileSize": 3218052910,
              "IsAlive": true,
              "Url": "https://www.fshare.vn/file/WOGWYU2EMLVBLU9",
              "Name": "The.Last.Ship.S04E02.1080p.AMZN.WEB-DL.DD5.1.H.264-QOQ.mkv"
            }
          ],
          "Intro": "Having lost their only lead, the crew of Nathan James continues their search for an item that could save the world. Chandler immerses himself in a mission for revenge.",
          "Poster": null,
          "Trailer": null,
          "Seasons": null,
          "Url": "https://fsharephim.com/episodes/the-last-ship-4x2/",
          "Name": "The Last Ship 4x2"
        },
        {
          "Id": "tvtxyo7V1345698",
          "Genres": [],
          "Images": [
            {
              "Thumbnail": "https://image.tmdb.org/t/p/w300/pZ6x7JcEDeCU8GjWy5aCn5OkoJl.jpg",
              "Url": "https://image.tmdb.org/t/p/original/pZ6x7JcEDeCU8GjWy5aCn5OkoJl.jpg",
              "Name": "The Last Ship 4&#215;3"
            }
          ],
          "Links": [
            {
              "OriginalLink": "https://fsharephim.com/links/tvtxyo7v1345698-2/",
              "Size": "--",
              "FileSize": 0,
              "IsAlive": false,
              "Url": "https://subscene.com/subtitles/the-last-ship-fourth-season/vietnamese/1621599",
              "Name": "Viet - Subtitle"
            },
            {
              "OriginalLink": "https://fsharephim.com/links/tvtxyo7v1345698/",
              "Size": "3.1 GB",
              "FileSize": 3363225437,
              "IsAlive": true,
              "Url": "https://www.fshare.vn/file/CPA257BQJ6XWHGL",
              "Name": "The.Last.Ship.S04E03.1080p.AMZN.WEB-DL.DD5.1.H.264-QOQ.mkv"
            }
          ],
          "Intro": "Nathan James&#8217;s crew searches for a precious item leading them to a strange place of opulence and violence where they cross paths with a most unexpected ally.",
          "Poster": null,
          "Trailer": null,
          "Seasons": null,
          "Url": "https://fsharephim.com/episodes/the-last-ship-4x3/",
          "Name": "The Last Ship 4x3"
        },
        {
          "Id": "tvtxyo7V1345699",
          "Genres": [],
          "Images": [
            {
              "Thumbnail": "https://image.tmdb.org/t/p/w300/hM9IB9lhZd8KEiFbLa3OlSoOGuK.jpg",
              "Url": "https://image.tmdb.org/t/p/original/hM9IB9lhZd8KEiFbLa3OlSoOGuK.jpg",
              "Name": "The Last Ship 4&#215;4"
            },
            {
              "Thumbnail": "https://image.tmdb.org/t/p/w300/60UvsKWYfguFq73WXzVh7iMpz1A.jpg",
              "Url": "https://image.tmdb.org/t/p/original/60UvsKWYfguFq73WXzVh7iMpz1A.jpg",
              "Name": "The Last Ship 4&#215;4"
            }
          ],
          "Links": [
            {
              "OriginalLink": "https://fsharephim.com/links/tvtxyo7v1345699-2/",
              "Size": "--",
              "FileSize": 0,
              "IsAlive": false,
              "Url": "https://subscene.com/subtitles/the-last-ship-fourth-season/vietnamese/1625181",
              "Name": "Viet - Subtitle"
            },
            {
              "OriginalLink": "https://fsharephim.com/links/tvtxyo7v1345699/",
              "Size": "2.7 GB",
              "FileSize": 2936890219,
              "IsAlive": true,
              "Url": "https://www.fshare.vn/file/VT79G7E57BPB6MD",
              "Name": "The.Last.Ship.S04E04.1080p.HDTV.X264-DIMENSION.mkv"
            }
          ],
          "Intro": "The crew searches for one of their own as enemies close in on all sides. Slattery is haunted by visions of the past.",
          "Poster": null,
          "Trailer": null,
          "Seasons": null,
          "Url": "https://fsharephim.com/episodes/the-last-ship-4x4/",
          "Name": "The Last Ship 4x4"
        },
        {
          "Id": "tvtxyo7V1345700",
          "Genres": [],
          "Images": [
            {
              "Thumbnail": "https://image.tmdb.org/t/p/w300/x5spZoFN6ANN8jRWq4S3xjgXcAA.jpg",
              "Url": "https://image.tmdb.org/t/p/original/x5spZoFN6ANN8jRWq4S3xjgXcAA.jpg",
              "Name": "The Last Ship 4&#215;5"
            },
            {
              "Thumbnail": "https://image.tmdb.org/t/p/w300/sOV47Y3r2KKTirl2j4a1hqvM6g7.jpg",
              "Url": "https://image.tmdb.org/t/p/original/sOV47Y3r2KKTirl2j4a1hqvM6g7.jpg",
              "Name": "The Last Ship 4&#215;5"
            }
          ],
          "Links": [
            {
              "OriginalLink": "https://fsharephim.com/links/tvtxyo7v1345700-2/",
              "Size": "--",
              "FileSize": 0,
              "IsAlive": false,
              "Url": "https://subscene.com/subtitles/the-last-ship-fourth-season/vietnamese/1629464",
              "Name": "Viet - Subtitle"
            },
            {
              "OriginalLink": "https://fsharephim.com/links/tvtxyo7v1345700/",
              "Size": "734.6 MB",
              "FileSize": 770279529,
              "IsAlive": true,
              "Url": "https://www.fshare.vn/file/FW28QP453OZLPJC",
              "Name": "The.Last.Ship.S04E05.720p.HDTV.X264.mkv"
            }
          ],
          "Intro": "Nathan James is diverted from their mission when they receive a suspicious distress call from a fishing trawler.",
          "Poster": null,
          "Trailer": null,
          "Seasons": null,
          "Url": "https://fsharephim.com/episodes/the-last-ship-4x5/",
          "Name": "The Last Ship 4x5"
        },
        {
          "Id": "tvtxyo7V1345701",
          "Genres": [],
          "Images": [
            {
              "Thumbnail": "https://image.tmdb.org/t/p/w300/buM4RVp0TuAWJnoEfBBmVKJMWXN.jpg",
              "Url": "https://image.tmdb.org/t/p/original/buM4RVp0TuAWJnoEfBBmVKJMWXN.jpg",
              "Name": "The Last Ship 4&#215;6"
            }
          ],
          "Links": [
            {
              "OriginalLink": "https://fsharephim.com/links/tvtxyo7v1345701-2/",
              "Size": "--",
              "FileSize": 0,
              "IsAlive": false,
              "Url": "https://subscene.com/subtitles/the-last-ship-fourth-season/vietnamese/1632529",
              "Name": "Viet - Subtitle"
            },
            {
              "OriginalLink": "https://fsharephim.com/links/tvtxyo7v1345701/",
              "Size": "1.1 GB",
              "FileSize": 1171508463,
              "IsAlive": true,
              "Url": "https://www.fshare.vn/file/QHWSY7VHIUFB2ZL",
              "Name": "The.Last.Ship.S04E06.720p.HDTV.X264.mkv"
            }
          ],
          "Intro": "With an enormous storm on the horizon, Nathan James must navigate an equally terrifying threat in order to make it to safety.",
          "Poster": null,
          "Trailer": null,
          "Seasons": null,
          "Url": "https://fsharephim.com/episodes/the-last-ship-4x6/",
          "Name": "The Last Ship 4x6"
        },
        {
          "Id": "tvtxyo7V1345702",
          "Genres": [],
          "Images": [
            {
              "Thumbnail": "https://image.tmdb.org/t/p/w300/b0y8OX8B13FwT8KMwBuzbEpT1el.jpg",
              "Url": "https://image.tmdb.org/t/p/original/b0y8OX8B13FwT8KMwBuzbEpT1el.jpg",
              "Name": "The Last Ship 4&#215;7"
            },
            {
              "Thumbnail": "https://image.tmdb.org/t/p/w300/qdXm1u69Cb7I3l2IFtBzjB108Bi.jpg",
              "Url": "https://image.tmdb.org/t/p/original/qdXm1u69Cb7I3l2IFtBzjB108Bi.jpg",
              "Name": "The Last Ship 4&#215;7"
            },
            {
              "Thumbnail": "https://image.tmdb.org/t/p/w300/5s84GWzYLZIr06rxDee8d3Ecxg5.jpg",
              "Url": "https://image.tmdb.org/t/p/original/5s84GWzYLZIr06rxDee8d3Ecxg5.jpg",
              "Name": "The Last Ship 4&#215;7"
            }
          ],
          "Links": [
            {
              "OriginalLink": "https://fsharephim.com/links/tvtxyo7v1345702-2/",
              "Size": "--",
              "FileSize": 0,
              "IsAlive": false,
              "Url": "https://subscene.com/subtitles/the-last-ship-fourth-season/vietnamese/1636069",
              "Name": "Viet - Subtitle"
            },
            {
              "OriginalLink": "https://fsharephim.com/links/tvtxyo7v1345702/",
              "Size": "1.1 GB",
              "FileSize": 1142502401,
              "IsAlive": true,
              "Url": "https://www.fshare.vn/file/4ARR9M6MFX5LAEU",
              "Name": "The.Last.Ship.S04E07.720p.HDTV.X264.mkv"
            }
          ],
          "Intro": "The search continues with a reconnaissance mission but things turn violent when an old foe resurfaces.",
          "Poster": null,
          "Trailer": null,
          "Seasons": null,
          "Url": "https://fsharephim.com/episodes/the-last-ship-4x7/",
          "Name": "The Last Ship 4x7"
        },
        {
          "Id": "tvtxyo7V1347242",
          "Genres": [],
          "Images": [
            {
              "Thumbnail": "https://image.tmdb.org/t/p/w300/krsZIX2KxbliWTFvTCu5XTxXW5x.jpg",
              "Url": "https://image.tmdb.org/t/p/original/krsZIX2KxbliWTFvTCu5XTxXW5x.jpg",
              "Name": "The Last Ship 4&#215;8"
            },
            {
              "Thumbnail": "https://image.tmdb.org/t/p/w300/xAb4St1W4g98uXxnJH2g4EHVuwZ.jpg",
              "Url": "https://image.tmdb.org/t/p/original/xAb4St1W4g98uXxnJH2g4EHVuwZ.jpg",
              "Name": "The Last Ship 4&#215;8"
            }
          ],
          "Links": [
            {
              "OriginalLink": "https://fsharephim.com/links/tvtxyo7v1347242-2/",
              "Size": "--",
              "FileSize": 0,
              "IsAlive": false,
              "Url": "https://subscene.com/subtitles/the-last-ship-fourth-season/vietnamese/1640090",
              "Name": "Viet - Subtitle"
            },
            {
              "OriginalLink": "https://fsharephim.com/links/tvtxyo7v1347242/",
              "Size": "1.1 GB",
              "FileSize": 1182989354,
              "IsAlive": true,
              "Url": "https://www.fshare.vn/file/QOV2EI3KF4Y95OO",
              "Name": "The.Last.Ship.S04E08.720p.HDTV.X264-DIMENSION.mkv"
            }
          ],
          "Intro": "An undercover mission in the land of the dead leads to disturbing revelations about Dr. Vellek&#8217;s sinister plans.",
          "Poster": null,
          "Trailer": null,
          "Seasons": null,
          "Url": "https://fsharephim.com/episodes/the-last-ship-4x8/",
          "Name": "The Last Ship 4x8"
        },
        {
          "Id": "tvtxyo7V1347243",
          "Genres": [],
          "Images": [
            {
              "Thumbnail": "https://image.tmdb.org/t/p/w300/nXwDhhXSDVpKi9OFMjM4Pd6IHp7.jpg",
              "Url": "https://image.tmdb.org/t/p/original/nXwDhhXSDVpKi9OFMjM4Pd6IHp7.jpg",
              "Name": "The Last Ship 4&#215;9"
            }
          ],
          "Links": [
            {
              "OriginalLink": "https://fsharephim.com/links/tvtxyo7v1347243-2/",
              "Size": "--",
              "FileSize": 0,
              "IsAlive": false,
              "Url": "https://subscene.com/subtitles/the-last-ship-fourth-season/vietnamese/1644514",
              "Name": "Viet - Subtitle"
            },
            {
              "OriginalLink": "https://fsharephim.com/links/tvtxyo7v1347243/",
              "Size": "1.1 GB",
              "FileSize": 1163427120,
              "IsAlive": true,
              "Url": "https://www.fshare.vn/file/7DV3HXYSR9LYRPY",
              "Name": "The.Last.Ship.S04E09.720p.HDTV.X264-DIMENSION.mkv"
            }
          ],
          "Intro": "The crew of Nathan James faces a threat that will test the limits of their Naval tactics and strategies.",
          "Poster": null,
          "Trailer": null,
          "Seasons": null,
          "Url": "https://fsharephim.com/episodes/the-last-ship-4x9/",
          "Name": "The Last Ship 4x9"
        }
      ],
      "Url": null,
      "Name": "Season 4 Aug. 20, 201710"
    }
  ],
  "Url": "https://fsharephim.com/tv-shows/the-last-ship/",
  "Name": "The Last Ship"
}