{
  "Id": null,
  "Genres": [
    {
      "Url": "https://fsharephim.com/genre/hanh-dong/",
      "Name": "Hành Động"
    },
    {
      "Url": "https://fsharephim.com/genre/khoa-hoc-vien-tuong/",
      "Name": "Khoa Học Viễn Tưởng"
    },
    {
      "Url": "https://fsharephim.com/genre/ky-ao/",
      "Name": "Kỳ Ảo"
    },
    {
      "Url": "https://fsharephim.com/genre/phieu-luu/",
      "Name": "Phiêu Lưu"
    }
  ],
  "Images": [
    {
      "Thumbnail": "https://image.tmdb.org/t/p/w300/5XPPB44RQGfkBrbJxmtdndKz05n.jpg",
      "Url": "https://image.tmdb.org/t/p/original/5XPPB44RQGfkBrbJxmtdndKz05n.jpg",
      "Name": "Thế Thân - Avatar"
    },
    {
      "Thumbnail": "https://image.tmdb.org/t/p/w300/xSxlmtLz2NYtO07N4WexY1y53pl.jpg",
      "Url": "https://image.tmdb.org/t/p/original/xSxlmtLz2NYtO07N4WexY1y53pl.jpg",
      "Name": "Thế Thân - Avatar"
    },
    {
      "Thumbnail": "https://image.tmdb.org/t/p/w300/rBIZCcDZsjJqcKp8YPzOVTQ8Gxx.jpg",
      "Url": "https://image.tmdb.org/t/p/original/rBIZCcDZsjJqcKp8YPzOVTQ8Gxx.jpg",
      "Name": "Thế Thân - Avatar"
    },
    {
      "Thumbnail": "https://image.tmdb.org/t/p/w300/ftbBuN9ZTuKLVu3nCWydOuRkoxa.jpg",
      "Url": "https://image.tmdb.org/t/p/original/ftbBuN9ZTuKLVu3nCWydOuRkoxa.jpg",
      "Name": "Thế Thân - Avatar"
    },
    {
      "Thumbnail": "https://image.tmdb.org/t/p/w300/uahkpugZE8Ke70eC9imMTxpwAoL.jpg",
      "Url": "https://image.tmdb.org/t/p/original/uahkpugZE8Ke70eC9imMTxpwAoL.jpg",
      "Name": "Thế Thân - Avatar"
    },
    {
      "Thumbnail": "https://image.tmdb.org/t/p/w300/dTJ9Hrin14vWGehvjfVK4OkzYE4.jpg",
      "Url": "https://image.tmdb.org/t/p/original/dTJ9Hrin14vWGehvjfVK4OkzYE4.jpg",
      "Name": "Thế Thân - Avatar"
    },
    {
      "Thumbnail": "https://image.tmdb.org/t/p/w300/lT1ntgWwogzdJZVyXZYacUrN0cb.jpg",
      "Url": "https://image.tmdb.org/t/p/original/lT1ntgWwogzdJZVyXZYacUrN0cb.jpg",
      "Name": "Thế Thân - Avatar"
    },
    {
      "Thumbnail": "https://image.tmdb.org/t/p/w300/hNIRu86pqw5asb80VZ3oagFEqYo.jpg",
      "Url": "https://image.tmdb.org/t/p/original/hNIRu86pqw5asb80VZ3oagFEqYo.jpg",
      "Name": "Thế Thân - Avatar"
    },
    {
      "Thumbnail": "https://image.tmdb.org/t/p/w300/kaUjj5yarOPpECEyJ6Z82EWdbgM.jpg",
      "Url": "https://image.tmdb.org/t/p/original/kaUjj5yarOPpECEyJ6Z82EWdbgM.jpg",
      "Name": "Thế Thân - Avatar"
    },
    {
      "Thumbnail": "https://image.tmdb.org/t/p/w300/aHcth2AXzZSjhX7JYh7ie73YVNc.jpg",
      "Url": "https://image.tmdb.org/t/p/original/aHcth2AXzZSjhX7JYh7ie73YVNc.jpg",
      "Name": "Thế Thân - Avatar"
    }
  ],
  "Links": [],
  "Intro": "Avatar là câu chuyện về người anh hùng “bất đắc dĩ” Jake Sully – một cựu sĩ quan thủy quân lục chiến bị liệt nửa thân. Người anh em sinh đôi của anh được chọn để tham gia vào chương trình cấy gien với người ngoài hành tinh Na’vi nhằm tạo ra một giống loài mới có thể hít thở không khí tại hành tinh Pandora. Giống người mới này được gọi là Avatar. Sau khi anh của Jake bị giết, Jake được chọn để thay thế anh mình và đã trở thành một Avatar, Jake có nhiệm vụ đi tìm hiểu và nghiên cứu hành tinh Pandora. Những thông tin mà anh thu thập được rất có giá trị cho chiến dịch xâm chiếm hành tinh xanh thứ hai này của loài người.",
  "Poster": "https://fsharephim.com/wp-content/uploads/2009/12/kmcqlZGaSh20zpTbuoF0Cdn07dT-185x278.jpg",
  "Trailer": "https://www.youtube.com/embed/5MB3Ea6L-gw?rel=0&amp;controls=1&amp;showinfo=0&autoplay=0",
  "Seasons": null,
  "Url": "https://fsharephim.com/movies/avatar/",
  "Name": "Thế Thân"
}