{
  "Id": null,
  "Genres": [
    {
      "Url": "https://fsharephim.com/genre/huyen-bi/",
      "Name": "Huyền Bí"
    },
    {
      "Url": "https://fsharephim.com/genre/kinh-di/",
      "Name": "Kinh Dị"
    },
    {
      "Url": "https://fsharephim.com/genre/thriller/",
      "Name": "Thriller"
    }
  ],
  "Images": [
    {
      "Thumbnail": "https://image.tmdb.org/t/p/w300/fgsHxz21B27hOOqQBiw9L6yWcM7.jpg",
      "Url": "https://image.tmdb.org/t/p/original/fgsHxz21B27hOOqQBiw9L6yWcM7.jpg",
      "Name": "Ác Quỷ Ma Sơ - The Nun"
    },
    {
      "Thumbnail": "https://image.tmdb.org/t/p/w300/tfKxFPq4lel0bL80H0C6kGYKGEq.jpg",
      "Url": "https://image.tmdb.org/t/p/original/tfKxFPq4lel0bL80H0C6kGYKGEq.jpg",
      "Name": "Ác Quỷ Ma Sơ - The Nun"
    },
    {
      "Thumbnail": "https://image.tmdb.org/t/p/w300/gcLGhjQTDOYYeCCx4EzVfSRWG43.jpg",
      "Url": "https://image.tmdb.org/t/p/original/gcLGhjQTDOYYeCCx4EzVfSRWG43.jpg",
      "Name": "Ác Quỷ Ma Sơ - The Nun"
    },
    {
      "Thumbnail": "https://image.tmdb.org/t/p/w300/ndGAaJj9jRrAYEYcCVCD2qoCS7Q.jpg",
      "Url": "https://image.tmdb.org/t/p/original/ndGAaJj9jRrAYEYcCVCD2qoCS7Q.jpg",
      "Name": "Ác Quỷ Ma Sơ - The Nun"
    }
  ],
  "Links": [],
  "Intro": "Ác quỷ ma sơ là một bộ phim về hiện tượng siêu linh kinh dị của Mỹ được đóng bởi đạo diễn James Wan vào năm 2017. Bộ phim được lấy tên một con quỷ trong bộ phim Ám ảnh kinh hoàng 2 tên Valak hay trong tiếng Anh là Valac, tiếng Pháp, tiếng Tây Ban Nha là Volac. Đây là một phim spin-off của phim Ám ảnh kinh hoàng 2",
  "Poster": "https://fsharephim.com/wp-content/uploads/2018/10/sFC1ElvoKGdHJIWRpNB3xWJ9lJA-185x278.jpg",
  "Trailer": "https://www.youtube.com/embed/pzD9zGcUNrw?rel=0&amp;controls=1&amp;showinfo=0&autoplay=0",
  "Seasons": null,
  "Url": "https://fsharephim.com/movies/the-nun/",
  "Name": "Ác Quỷ Ma Sơ"
}