{
  "Id": "49883",
  "Genres": [],
  "Images": [],
  "Links": [
    {
      "OriginalLink": null,
      "Size": null,
      "FileSize": 0,
      "IsAlive": false,
      "Url": "https://www.fshare.vn/file/QAXJOGX29RTL",
      "Name": null
    },
    {
      "OriginalLink": null,
      "Size": null,
      "FileSize": 0,
      "IsAlive": false,
      "Url": "https://www.fshare.vn/file/QAXJOGX29RTL",
      "Name": null
    }
  ],
  "Intro": null,
  "Poster": null,
  "Trailer": null,
  "Seasons": null,
  "Url": "https://taiphimhd.com/threads/inside-out-2015-720p-bluray-dd5-1-x264-wiki-nhung-manh-ghep-cam-xuc.31763/",
  "Name": "FS 4S Inside Out 2015 720p BluRay DD5.1 x264-WiKi - Những Mảnh Ghép Cảm Xúc"
}