{
  "Id": "55986",
  "Genres": [],
  "Images": [],
  "Links": [
    {
      "OriginalLink": null,
      "Size": null,
      "FileSize": 0,
      "IsAlive": false,
      "Url": "https://www.fshare.vn/file/R53Q8L27IQUS",
      "Name": null
    },
    {
      "OriginalLink": null,
      "Size": null,
      "FileSize": 0,
      "IsAlive": false,
      "Url": "https://www.fshare.vn/file/R53Q8L27IQUS",
      "Name": null
    }
  ],
  "Intro": null,
  "Poster": null,
  "Trailer": null,
  "Seasons": null,
  "Url": "https://taiphimhd.com/threads/rise-of-the-guardians-2012-vie-720p-bluray-dd5-1-x264-vav-su-troi-day-cua-cac-ve-than-hugh-jackman-alec-baldwin-isla-fisher-phu-de.35984/",
  "Name": "FS Rise of the Guardians 2012 ViE 720p BluRay DD5.1 x264-VAV ~ Sự trỗi dậy của các Vệ thần | Hugh Jackman, Alec Baldwin, Isla Fisher (Phụ đề)"
}