{
  "Id": "34076",
  "Genres": [],
  "Images": [],
  "Links": [
    {
      "OriginalLink": null,
      "Size": null,
      "FileSize": 0,
      "IsAlive": false,
      "Url": "https://www.fshare.vn/file/TNIDZNYLRVS5",
      "Name": null
    },
    {
      "OriginalLink": null,
      "Size": null,
      "FileSize": 0,
      "IsAlive": false,
      "Url": "https://www.fshare.vn/file/TNIDZNYLRVS5",
      "Name": null
    },
    {
      "OriginalLink": null,
      "Size": null,
      "FileSize": 0,
      "IsAlive": false,
      "Url": "https://www.fshare.vn/file/TNIDZNYLRVS5",
      "Name": null
    },
    {
      "OriginalLink": null,
      "Size": null,
      "FileSize": 0,
      "IsAlive": false,
      "Url": "https://www.fshare.vn/file/TNIDZNYLRVS5",
      "Name": null
    }
  ],
  "Intro": null,
  "Poster": null,
  "Trailer": null,
  "Seasons": null,
  "Url": "https://taiphimhd.com/threads/shaun-the-sheep-movie-2015-720p-bluray-dd5-1-x264-don-cuu-que-ra-pho-justin-fletcher-john-sparkes-omid-djalili-phu-de.22034/",
  "Name": "FS Shaun the Sheep Movie 2015 720p BluRay DD5.1 x264-DON ~ Cừu Quê Ra Phố | Justin Fletcher, John Sparkes, Omid Djalili (Phụ đề)"
}