{
  "Id": "41083",
  "Genres": [],
  "Images": [],
  "Links": [
    {
      "OriginalLink": null,
      "Size": null,
      "FileSize": 0,
      "IsAlive": false,
      "Url": "https://www.fshare.vn/file/YA7TAN4FIXXK",
      "Name": null
    },
    {
      "OriginalLink": null,
      "Size": null,
      "FileSize": 0,
      "IsAlive": false,
      "Url": "https://www.fshare.vn/file/YA7TAN4FIXXK",
      "Name": null
    },
    {
      "OriginalLink": null,
      "Size": null,
      "FileSize": 0,
      "IsAlive": false,
      "Url": "https://www.fshare.vn/file/YA7TAN4FIXXK",
      "Name": null
    },
    {
      "OriginalLink": null,
      "Size": null,
      "FileSize": 0,
      "IsAlive": false,
      "Url": "https://www.fshare.vn/file/YA7TAN4FIXXK",
      "Name": null
    }
  ],
  "Intro": null,
  "Poster": null,
  "Trailer": null,
  "Seasons": null,
  "Url": "https://taiphimhd.com/threads/the-swan-princess-a-royal-family-tale-2014-720p-hdtv-aac2-0-h-264-ntv-cong-chua-thien-nga-cau-chuyen-hoang-gia-phu-de.26064/",
  "Name": "FS The Swan Princess: A Royal Family Tale 2014 720p HDTV AAC2.0 H.264-NTV ~ Công chúa Thiên Nga: Câu chuyện hoàng gia (Phụ đề)"
}