{
  "Id": "41184",
  "Genres": [],
  "Images": [],
  "Links": [
    {
      "OriginalLink": null,
      "Size": null,
      "FileSize": 0,
      "IsAlive": false,
      "Url": "https://www.fshare.vn/file/AIGIWRVQVUCU",
      "Name": null
    },
    {
      "OriginalLink": null,
      "Size": null,
      "FileSize": 0,
      "IsAlive": false,
      "Url": "https://www.fshare.vn/file/AIGIWRVQVUCU",
      "Name": null
    },
    {
      "OriginalLink": null,
      "Size": null,
      "FileSize": 0,
      "IsAlive": false,
      "Url": "https://www.fshare.vn/file/AIGIWRVQVUCU",
      "Name": null
    },
    {
      "OriginalLink": null,
      "Size": null,
      "FileSize": 0,
      "IsAlive": false,
      "Url": "https://www.fshare.vn/file/AIGIWRVQVUCU",
      "Name": null
    }
  ],
  "Intro": null,
  "Poster": null,
  "Trailer": null,
  "Seasons": null,
  "Url": "https://taiphimhd.com/threads/transformers-prime-beast-hunters-predacons-rising-2013-vie-720p-bluray-dts-x264-sadpanda-nguoi-may-bien-hinh-predacons-noi-day-phu-de.26135/",
  "Name": "FS Transformers Prime Beast Hunters: Predacons Rising 2013 ViE 720p BluRay DTS x264-SADPANDA ~ Người Máy Biến Hình: Predacons Nổi Dậy (Phụ đề)"
}