{
  "Id": "9472",
  "Genres": [],
  "Images": [],
  "Links": [
    {
      "OriginalLink": null,
      "Size": null,
      "FileSize": 0,
      "IsAlive": false,
      "Url": "http://www.fshare.vn/file/TXH1Y4K1FT",
      "Name": null
    }
  ],
  "Intro": null,
  "Poster": null,
  "Trailer": null,
  "Seasons": null,
  "Url": "https://taiphimhd.com/threads/thomas-friends-tale-of-the-brave-2014-mhd-bluray-dd5-1-x264-epik-thomas-va-nhung-nguoi-ban.6198/",
  "Name": "FS Thomas &amp; Friends: Tale Of The Brave 2014 mHD BluRay DD5.1 x264-EPiK ~Thomas Và Những Người Bạn"
}