{
  "Id": "2236",
  "Genres": [],
  "Images": [],
  "Links": [
    {
      "OriginalLink": null,
      "Size": " 2.64 GB",
      "FileSize": 2832415264,
      "IsAlive": true,
      "Url": "https://www.fshare.vn/file/T3096F20NT",
      "Name": "Tinker.Bell.And.The.Pirate.Fairy.2014.720p.BluRay.DTS.x264-PublicHD.mkv"
    },
    {
      "OriginalLink": null,
      "Size": " 2.64 GB",
      "FileSize": 2832415264,
      "IsAlive": true,
      "Url": "https://www.fshare.vn/file/T3096F20NT",
      "Name": "Tinker.Bell.And.The.Pirate.Fairy.2014.720p.BluRay.DTS.x264-PublicHD.mkv"
    }
  ],
  "Intro": null,
  "Poster": null,
  "Trailer": null,
  "Seasons": null,
  "Url": "https://taiphimhd.com/threads/tinker-bell-and-the-pirate-fairy-2014-tinker-bell-va-cac-nang-tien-hai-tac-2014.1219/",
  "Name": "Tinker Bell And The Pirate Fairy 2014 | Tinker Bell Và Các Nàng Tiên Hải Tặc 2014"
}